file_tree_display/__init__.py
file_tree_display/__main__.py
file_tree_display/__version__.py
file_tree_display/_constants.py
file_tree_display/ftd.py
file_tree_display-1.2.4.dist-info/METADATA
file_tree_display-1.2.4.dist-info/WHEEL
file_tree_display-1.2.4.dist-info/entry_points.txt
file_tree_display-1.2.4.dist-info/licenses/LICENSE
file_tree_display-1.2.4.dist-info/RECORD
