Metadata-Version: 2.4
Name: file_tree_display
Version: 1.2.4
Summary: A utility for generating a visually structured directory tree.
Project-URL: Homepage, https://github.com/yaronday/file_tree_display
Project-URL: Issues, https://github.com/yaronday/file_tree_display/issues
Project-URL: license, https://github.com/yaronday/file_tree_display/blob/master/LICENSE
Author-email: Yaron Dayan <yaronday77@gmail.com>
License: MIT
License-File: LICENSE
Classifier: Operating System :: OS Independent
Classifier: Programming Language :: Python :: 3
Requires-Python: >=3.10
Requires-Dist: build>=1.3.0
Requires-Dist: nano-dev-utils>=1.7.0
